pytest_httpchain_mcp/__init__.py
pytest_httpchain_mcp/cli.py
pytest_httpchain_mcp/server.py
pytest_httpchain_mcp-0.2.1.dist-info/WHEEL
pytest_httpchain_mcp-0.2.1.dist-info/entry_points.txt
pytest_httpchain_mcp-0.2.1.dist-info/METADATA
pytest_httpchain_mcp-0.2.1.dist-info/RECORD
