Metadata-Version: 2.3
Name: pytest-httpchain-mcp
Version: 0.2.1
Summary: MCP server for pytest-httpchain
Author: Alexander Eresov
Author-email: Alexander Eresov <aeresov@gmail.com>
Requires-Dist: mcp[cli]>=1.11.0
Requires-Python: >=3.13
